{
  "rows": [
    {
      "id": 1,
      "czf": "上海市城市交通管理局",
      "htsj": "",
      "yzj": "89361",
      "dz":"主楼底层（大堂两侧及南面）、主楼三层、主楼四层、裙房四层",
      "zj1":"89361",
      "zj2":"89361",
      "zj3":"89361",
      "zj4":"89361",
      "zj5":"89361",
      "zj6":"89361",
      "zj7":"89361",
      "zj8":"89361",
      "zj9":"89361",
      "zj10":"89361",
      "zj11":"89361",
      "zj12":"89361"
    },
    {
      "id": 2,
      "czf": "上海懿达物流有限公司",
      "htsj": "2016.3.1-2019.1.31",
      "yzj": "4375",
      "dz":"201-202",
      "zj1":"4375",
      "zj2":"4375",
      "zj3":"4375",
      "zj4":"4375",
      "zj5":"4375",
      "zj6":"4375",
      "zj7":"4375",
      "zj8":"4375",
      "zj9":"4375",
      "zj10":"4375",
      "zj11":"4375",
      "zj12":"4375"
    },
    {
      "id": 3,
      "czf": "上海桑迪精细化工研究所有限公司",
      "htsj": "2016.1.1-2017.12.31",
      "yzj": "4375",
      "dz":"203-204",
      "zj1":"4375",
      "zj2":"4375",
      "zj3":"4375",
      "zj4":"4375",
      "zj5":"4375",
      "zj6":"4375",
      "zj7":"4375",
      "zj8":"4375",
      "zj9":"4375",
      "zj10":"4375",
      "zj11":"4375",
      "zj12":"4375"
    },
    {
      "id": 4,
      "czf": "上海桑迪精细化工研究所有限公司",
      "htsj": "2018.1.1-2019.12.31",
      "yzj": "4375",
      "dz":"203-204",
      "zj1":"4375",
      "zj2":"4375",
      "zj3":"4375",
      "zj4":"4375",
      "zj5":"4375",
      "zj6":"4375",
      "zj7":"4375",
      "zj8":"4375",
      "zj9":"4375",
      "zj10":"4375",
      "zj11":"4375",
      "zj12":"4375"
    }
  ],
  "total": 4,
  "maxResults": 10,
  "currentPage": 0,
  "records": 3,
  "firstResult": -10
}